Metadata-Version: 2.4
Name: gemseo-vimseo
Version: 6.0.0
Summary: Temporary version of GEMSEO for VIMSEO
Author-email: VIMSEO developers <sebastien.bocquet@irt-saintexupery.com>
License: GNU Lesser General Public License v3
Project-URL: Homepage, https://gitlab.com/SebastienBocquet-IRT/gemseo
Project-URL: Documentation, https://gemseo.readthedocs.io
Project-URL: Source, https://gitlab.com/SebastienBocquet-IRT/gemseo
Project-URL: Tracker, https://gitlab.com/SebastienBocquet-IRT/gemseo/-/issues
Classifier: License :: OSI Approved :: GNU Lesser General Public License v3 (LGPLv3)
Classifier: Intended Audience :: Science/Research
Classifier: Topic :: Scientific/Engineering
Classifier: Operating System :: POSIX :: Linux
Classifier: Operating System :: MacOS
Classifier: Operating System :: Microsoft :: Windows
Classifier: Programming Language :: Python :: 3 :: Only
Classifier: Programming Language :: Python :: 3.9
Classifier: Programming Language :: Python :: 3.10
Classifier: Programming Language :: Python :: 3.11
Classifier: Programming Language :: Python :: 3.12
Requires-Python: <3.13,>=3.9
License-File: LICENSE.txt
License-File: CREDITS.rst
Requires-Dist: docstring-inheritance<=2.2.1,>=1.0.0
Requires-Dist: eval-type-backport==0.2.0; python_version < "3.10"
Requires-Dist: fastjsonschema<=2.20.0,>=2.14.5
Requires-Dist: genson<=1.3.0,>=1.2.2
Requires-Dist: h5py<=3.11.0,>=3.0.0
Requires-Dist: importlib-metadata>=3.6; python_version < "3.10"
Requires-Dist: jinja2<=3.1.4,>=3.0.0
Requires-Dist: matplotlib<=3.9.2,>=3.3.0
Requires-Dist: networkx<=3.3,>=2.5
Requires-Dist: numpy<=1.26.4,>=1.22
Requires-Dist: packaging<=24.1,>=15
Requires-Dist: pandas<=2.2.2,>=1.3.0
Requires-Dist: pyxdsm<=2.3.0,>=2.1.0
Requires-Dist: pydantic<=2.9.1,>=2.1
Requires-Dist: requests<3
Requires-Dist: scipy<=1.14.1,>=1.9
Requires-Dist: strenum<=0.4.15,>=0.4.9
Requires-Dist: tqdm<=4.66.5,>=4.41
Requires-Dist: typing-extensions<5,>=4
Requires-Dist: xdsmjs<=2.0.0,>=1.0.0
Requires-Dist: xxhash<=3.5.0,>=3.0.0
Provides-Extra: all
Requires-Dist: graphviz<=0.20.3,>=0.16; extra == "all"
Requires-Dist: nlopt<=2.7.1,>=2.7.0; extra == "all"
Requires-Dist: openpyxl<=3.1.5,>=3; extra == "all"
Requires-Dist: openturns<=1.24,>=1.19; extra == "all"
Requires-Dist: pyDOE3<=1.0.4,>=1.0.1; extra == "all"
Requires-Dist: scikit-learn<=1.5.2,>=1; extra == "all"
Requires-Dist: sympy<=1.13.2,>=1.5; extra == "all"
Requires-Dist: xlwings<=0.30.4,>=0.27.0; platform_system == "Windows" and extra == "all"
Requires-Dist: pillow<=10.4.0,>=9.5.0; extra == "all"
Requires-Dist: plotly<=5.24.0,>=5.7.0; extra == "all"
Provides-Extra: test
Requires-Dist: covdefaults; extra == "test"
Requires-Dist: pandera; extra == "test"
Requires-Dist: pytest>=7; extra == "test"
Requires-Dist: pytest-cov>=5; extra == "test"
Requires-Dist: pytest-xdist>=3; extra == "test"
Provides-Extra: doc
Requires-Dist: autodoc_pydantic; extra == "doc"
Requires-Dist: autodocsumm; extra == "doc"
Requires-Dist: setuptools; extra == "doc"
Requires-Dist: pandera; extra == "doc"
Requires-Dist: pillow; extra == "doc"
Requires-Dist: pydata-sphinx-theme; extra == "doc"
Requires-Dist: pyenchant; extra == "doc"
Requires-Dist: sphinx; extra == "doc"
Requires-Dist: sphinx-design; extra == "doc"
Requires-Dist: sphinx_gallery; extra == "doc"
Requires-Dist: sphinxcontrib.apidoc; extra == "doc"
Requires-Dist: sphinxcontrib.bibtex; extra == "doc"
Requires-Dist: sphinxcontrib.plantuml; extra == "doc"
Requires-Dist: sphinxcontrib.spelling; extra == "doc"
Dynamic: license-file
